{
  "name": "t:sections.header.name",
  "type": "header",
  "sections": {
    "announcement_bar_UwDya9": {
      "type": "announcement-bar",
      "blocks": {
        "announcement_WgtBdc": {
          "type": "announcement",
          "settings": {
            "text": "Welcome to our store",
            "link": ""
          }
        },
        "announcement_4mBLna": {
          "type": "announcement",
          "settings": {
            "text": "Welcome to our store",
            "link": ""
          }
        }
      },
      "block_order": [
        "announcement_WgtBdc",
        "announcement_4mBLna"
      ],
      "settings": {
        "color_scheme": "scheme-d2de991f-3d49-437a-9020-46313d96a742",
        "show_line_separator": true,
        "show_social": false,
        "auto_rotate": false,
        "change_slides_speed": 5,
        "enable_country_selector": false,
        "enable_language_selector": false
      }
    },
    "header": {
      "type": "header",
      "settings": {
        "logo_position": "middle-left",
        "menu": "main-menu",
        "menu_type_desktop": "dropdown",
        "sticky_header_type": "on-scroll-up",
        "show_line_separator": true,
        "color_scheme": "scheme-1",
        "menu_color_scheme": "scheme-1",
        "enable_country_selector": false,
        "enable_language_selector": false,
        "mobile_logo_position": "center",
        "margin_bottom": 0,
        "padding_top": 4,
        "padding_bottom": 4
      }
    }
  },
  "order": [
    "announcement_bar_UwDya9",
    "header"
  ]
}
